clgi/__init__.py
clgi/app.py
clgi/argparser.py
clgi/errors.py
clgi/tty.py
clgi-0.0.1.dist-info/LICENSE.txt
clgi-0.0.1.dist-info/METADATA
clgi-0.0.1.dist-info/WHEEL
clgi-0.0.1.dist-info/top_level.txt
clgi-0.0.1.dist-info/RECORD
