Metadata-Version: 2.1
Name: clgi
Version: 0.0.1
Summary: A restructured object notation
Author-email: tef <tef@printf.net>
Project-URL: Homepage, https://github.com/tef/clgi
Project-URL: Bug Tracker, https://github.com/tef/clgi/issues
Classifier: Programming Language :: Python :: 3
Classifier: License :: OSI Approved :: MIT License
Classifier: Operating System :: OS Independent
Requires-Python: >=3.6
License-File: LICENSE.txt
